pyAtmosLogger/__init__.py
pyAtmosLogger/instruments/__init__.py
pyAtmosLogger/instruments/bronkhorst_mfc_default.py
pyAtmosLogger/instruments/ott_parsivel2_actris.py
pyAtmosLogger/instruments/pyAtmosLogger_dummy_1.py
pyAtmosLogger/instruments/thies_laserprecipitationmonitor_actris.py
pyAtmosLogger/instruments/tsi_ops3330_default.py
pyAtmosLogger/pyAtmosLogger.py
pyAtmosLogger/utils/__init__.py
pyAtmosLogger/utils/utils.py
pyatmoslogger-0.7.dist-info/LICENSE.txt
pyatmoslogger-0.7.dist-info/METADATA
pyatmoslogger-0.7.dist-info/WHEEL
pyatmoslogger-0.7.dist-info/entry_points.txt
pyatmoslogger-0.7.dist-info/RECORD
