Metadata-Version: 2.1
Name: pyAtmosLogger
Version: 0.7
Summary: Python Data Logger for Atmospheric Application
Home-page: https://github.com/marcusgmueller/pyAtmosLogger
License: MIT
Author: Marcus G. Müller
Classifier: License :: OSI Approved :: MIT License
Classifier: Programming Language :: Python :: 2
Classifier: Programming Language :: Python :: 2.7
Classifier: Programming Language :: Python :: 3
Classifier: Programming Language :: Python :: 3.4
Classifier: Programming Language :: Python :: 3.5
Classifier: Programming Language :: Python :: 3.6
Classifier: Programming Language :: Python :: 3.7
Classifier: Programming Language :: Python :: 3.8
Classifier: Programming Language :: Python :: 3.9
Classifier: Programming Language :: Python :: 3.10
Classifier: Programming Language :: Python :: 3.11
Classifier: Programming Language :: Python :: 3.12
Requires-Dist: argparse
Requires-Dist: minimalmodbus
Requires-Dist: numpy
Requires-Dist: pandas
Requires-Dist: pause
Requires-Dist: pySerial
Requires-Dist: pytz
Requires-Dist: pyyaml
Requires-Dist: scipy
Requires-Dist: tzlocal
Requires-Dist: xarray
Project-URL: Documentation, https://pyatmoslogger.readthedocs.io/en/latest/index.html
Project-URL: Repository, https://github.com/marcusgmueller/pyAtmosLogger
